LICENSE.txt
setup.cfg
setup.py
ML360_imgprepro_DP/ML360_imgprepro_DP.py
ML360_imgprepro_DP/__init__.py
ML360_imgprepro_DP.egg-info/PKG-INFO
ML360_imgprepro_DP.egg-info/SOURCES.txt
ML360_imgprepro_DP.egg-info/dependency_links.txt
ML360_imgprepro_DP.egg-info/requires.txt
ML360_imgprepro_DP.egg-info/top_level.txt