Metadata-Version: 2.1
Name: ML360-imgprepro-DP
Version: 0.0.2
Summary: Image Preprocessing library
Home-page:  
Download-URL:  
Author: Harsha Teja Bolla
Author-email: mlharshateja@gmail.com
License: MIT
Keywords: Image,Preprocessing,opencv,tensorflow,Transformers,augmentation
Platform: UNKNOWN
Classifier: Development Status :: 3 - Alpha
Classifier: Intended Audience :: Developers
Classifier: Topic :: Software Development :: Build Tools
Classifier: License :: OSI Approved :: MIT License
Classifier: Programming Language :: Python :: 3
Classifier: Programming Language :: Python :: 3.4
Classifier: Programming Language :: Python :: 3.5
Classifier: Programming Language :: Python :: 3.6
License-File: LICENSE.txt
